{"version":1,"resource":"file:///c%3A/Users/ahofer/Documents/Projekte/MarpPresentation/data/nvhbrake.drawio","entries":[{"id":"yhnF.drawio","source":"Workspace Edit","timestamp":1662444754003},{"id":"Pbl3.drawio","source":"Workspace Edit","timestamp":1662445241954},{"id":"eOgZ.drawio","source":"Workspace Edit","timestamp":1662451254976},{"id":"WvMH.drawio","source":"Workspace Edit","timestamp":1662452800793},{"id":"ULJJ.drawio","source":"Workspace Edit","timestamp":1662453077856},{"id":"e0Qi.drawio","source":"Workspace Edit","timestamp":1662454545221},{"id":"GrjR.drawio","source":"Workspace Edit","timestamp":1662455621797}]}